dpd_info_client_api/api.py
dpd_info_client_api/infoapi.py
dpd_info_client_api/settings.py
dpd_info_client_api/__init__.py
dpd_info_client_api-0.4.dist-info/DESCRIPTION.rst
dpd_info_client_api-0.4.dist-info/METADATA
dpd_info_client_api-0.4.dist-info/metadata.json
dpd_info_client_api-0.4.dist-info/RECORD
dpd_info_client_api-0.4.dist-info/top_level.txt
dpd_info_client_api-0.4.dist-info/WHEEL
dpd_info_client_api-0.4.dist-info/zip-safe
